jsc_custom/__init__.py
jsc_custom/_version.py
jsc_custom/misc.py
jsc_custom/apihandler/__init__.py
jsc_custom/apihandler/db_health.py
jsc_custom/apihandler/frontend.py
jsc_custom/apihandler/incidents.py
jsc_custom/apihandler/misc.py
jsc_custom/apihandler/self_api_handler_oauth.py
jsc_custom/apihandler/share_button.py
jsc_custom/apihandler/slurm_wrapper.py
jsc_custom/apihandler/trigger_reauth.py
jsc_custom/apihandler/tunnel_restart.py
jsc_custom/apihandler/user_count.py
jsc_custom/apihandler/workshops_manage.py
jsc_custom/authenticator/__init__.py
jsc_custom/authenticator/oauthenticator.py
jsc_custom/handler/__init__.py
jsc_custom/handler/credits_handler.py
jsc_custom/handler/page_handlers.py
jsc_custom/handler/share_handler.py
jsc_custom/handler/workshop_manage.py
jsc_custom/orm/__init__.py
jsc_custom/orm/share.py
jsc_custom/orm/workshops.py
jsc_custom/proxy/__init__.py
jsc_custom/proxy/custom.py
jsc_custom/spawner/__init__.py
jsc_custom/spawner/api_encrypt.py
jsc_custom/spawner/api_notifications_sse.py
jsc_custom/spawner/api_options_form.py
jsc_custom/spawner/api_spawn_options_update.py
jsc_custom/spawner/api_start_server_random_name.py
jsc_custom/spawner/spawner.py
jsc_custom/spawner/utils.py
jupyter_jsc_custom-2.3.10.dist-info/METADATA
jupyter_jsc_custom-2.3.10.dist-info/WHEEL
jupyter_jsc_custom-2.3.10.dist-info/licenses/LICENSE
jupyter_jsc_custom-2.3.10.dist-info/RECORD
