Metadata-Version: 2.4
Name: jupyter-jsc-custom
Version: 2.3.10
Summary: Helper classes and functions, used for JupyterHubs running at Juelich Supercomputing centre
Author-email: Tim Kreuzer <t.kreuzer@fz-juelich.de>
License: BSD 3-Clause License
License-File: LICENSE
Keywords: jupyterhub
Requires-Python: >=3.9
Requires-Dist: aiohttp
Requires-Dist: datefinder
Requires-Dist: escapism
Requires-Dist: etcdpy
Requires-Dist: jinja2
Requires-Dist: jsonformatter
Requires-Dist: jupyterhub-forwardbasespawner>=2.0.0
Requires-Dist: jupyterhub-outpostspawner>=2.0.0
Requires-Dist: jupyterhub-traefik-proxy==2.1.0
Requires-Dist: jupyterhub-unicorespawner>=2.0.0
Requires-Dist: jupyterhub>=5.0.0
Requires-Dist: m2crypto
Requires-Dist: oauthenticator
Requires-Dist: pyyaml
Requires-Dist: traitlets
Requires-Dist: urllib3
